mlserver_alibi_detect/__init__.py
mlserver_alibi_detect/runtime.py
mlserver_alibi_detect/version.py
mlserver_alibi_detect-1.6.1.dist-info/LICENSE
mlserver_alibi_detect-1.6.1.dist-info/METADATA
mlserver_alibi_detect-1.6.1.dist-info/WHEEL
mlserver_alibi_detect-1.6.1.dist-info/RECORD
